ryerrabelli/__init__.py
ryerrabelli/_version.py
ryerrabelli/constants.py
ryerrabelli/decorators.py
ryerrabelli/packaging.py
ryerrabelli/utils.py
ryerrabelli-1.0.62.dist-info/METADATA
ryerrabelli-1.0.62.dist-info/WHEEL
ryerrabelli-1.0.62.dist-info/top_level.txt
ryerrabelli-1.0.62.dist-info/RECORD
