Metadata-Version: 2.1
Name: ryerrabelli
Version: 1.0.62
Summary: See long description
Home-page: https://github.com/ryerrabelli/ryerrabelli
Author: Rahul Yerrabelli
Author-email: ryerrabelli+python@gmail.com
License: UNKNOWN
Platform: UNKNOWN
Classifier: Development Status :: 3 - Alpha
Classifier: Intended Audience :: Developers
Classifier: Topic :: Software Development :: Build Tools
Classifier: License :: OSI Approved :: MIT License
Classifier: Programming Language :: Python :: 3 :: Only
Classifier: Programming Language :: Python :: 3.6
Classifier: Programming Language :: Python :: 3.7
Classifier: Programming Language :: Python :: 3.8
Classifier: Programming Language :: Python :: 3.9
Classifier: Environment :: MacOS X
Classifier: Natural Language :: English
Requires-Python: >=3.6
Requires-Dist: versioneer (~=0.19)
Requires-Dist: setuptools (~=56.2.0)
